{"code":"G03016","total":{"LDF":3,"UDF":7,"BJP+":2,"OTH":1},"name":"Thottappuzhassery","wardCd":"G03016010","gw":{"G03016011":{"name":"CHALAIKKARA","cand":{"canCd":"2","name":"JOY PORON","party":"IND(LDF)","votes":"241","pos":"1","pg":"LDF"}},"G03016002":{"name":"CHARALKUNNU","cand":{"canCd":"1","name":"ANEESH KUMAR C S","party":"INC","votes":"242","pos":"1","pg":"UDF"}},"G03016012":{"name":"CHIRAYIRAMPU","cand":{"canCd":"3","name":"LATHA CHANDRAN","party":"INC","votes":"265","pos":"1","pg":"UDF"}},"G03016001":{"name":"KALLIPPARA","cand":{"canCd":"4","name":"SHERIN","party":"INC","votes":"324","pos":"1","pg":"UDF"}},"G03016006":{"name":"KATTEPURAM","cand":{"canCd":"1","name":"ELSY","party":"INC","votes":"402","pos":"1","pg":"UDF"}},"G03016005":{"name":"KURIYANOOR","cand":{"canCd":"3","name":"BIJU J GEORGE","party":"INC","votes":"333","pos":"1","pg":"UDF"}},"G03016003":{"name":"MARAMKOLLI","cand":{"canCd":"1","name":"MANJU VARGHESE","party":"IND(LDF)","votes":"321","pos":"1","pg":"LDF"}},"G03016008":{"name":"MARAMON","cand":{"canCd":"1","name":"GOPALKRISHNAN(SOMAN)","party":"INC","votes":"300","pos":"1","pg":"UDF"}},"G03016007":{"name":"NEDUMPRAYAR","cand":{"canCd":"1","name":"MANJU LAKSHMI","party":"INC","votes":"311","pos":"1","pg":"UDF"}},"G03016004":{"name":"PONMALA","cand":{"canCd":"1","name":"AJITHA KUMARI N K(PRIYA PAZHAYIDATHIL)","party":"IND","votes":"345","pos":"1","pg":"OTH"}},"G03016013":{"name":"THONIPPUZHA","cand":{"canCd":"2","name":"SARAMMA(AMMINI TEACHER)","party":"IND(LDF)","votes":"359","pos":"1","pg":"LDF"}},"G03016009":{"name":"THOTTAPPUZHASSERY","cand":{"canCd":"2","name":"PRAKASH ","party":"BJP","votes":"274","pos":"1","pg":"BJP+"}},"G03016010":{"name":"VELLANGOOR","cand":{"canCd":"1","name":"USHA KUMARI(SANTHI CHERUKADU)","party":"BJP","votes":"249","pos":"1","pg":"BJP+"}}}}






