{"code":"G04007","total":{"LDF":3,"UDF":7,"BJP+":2,"OTH":4},"name":"Ezhupunna","wardCd":"G04007004","gw":{"G04007007":{"name":"ERAMALLOOR","cand":{"canCd":"1","name":"GEETHA DINESAN","party":"IND","votes":"418","pos":"1","pg":"OTH"}},"G04007001":{"name":"KALLUPURAKKAL","cand":{"canCd":"1","name":"JULIET ( JULY THOMAS)","party":"INC","votes":"571","pos":"1","pg":"UDF"}},"G04007005":{"name":"KANJIRATHUNGAL","cand":{"canCd":"2","name":"SINDHU","party":"BJP","votes":"338","pos":"1","pg":"BJP+"}},"G04007011":{"name":"KANNUKULANGARA","cand":{"canCd":"3","name":"N.K.RAJEEVAN","party":"INC","votes":"489","pos":"1","pg":"UDF"}},"G04007013":{"name":"KONKERIL","cand":{"canCd":"2","name":"BINDU SHAJI","party":"INC","votes":"418","pos":"1","pg":"UDF"}},"G04007006":{"name":"KONNANATTU","cand":{"canCd":"2","name":"MAYA RAVI","party":"CPI","votes":"431","pos":"1","pg":"LDF"}},"G04007009":{"name":"KOVILAKAM","cand":{"canCd":"1","name":"BINUMOL.A.P","party":"CPI(M)","votes":"345","pos":"1","pg":"LDF"}},"G04007016":{"name":"KUMARAPURAM","cand":{"canCd":"1","name":"UMMACHAN PAUL","party":"IND","votes":"244","pos":"1","pg":"OTH"}},"G04007012":{"name":"MARKET","cand":{"canCd":"7","name":"SHAJI KUREETHARA","party":"RSP","votes":"366","pos":"1","pg":"UDF"}},"G04007015":{"name":"NEENDAKARA","cand":{"canCd":"1","name":"JOJAN RAPHAEL","party":"IND","votes":"415","pos":"1","pg":"OTH"}},"G04007010":{"name":"PANCHAYATH OFFICE","cand":{"canCd":"3","name":"SHABUMON (SHABURAJ)","party":"BJP","votes":"327","pos":"1","pg":"BJP+"}},"G04007003":{"name":"SREENARAYANAPURAM","cand":{"canCd":"2","name":"V.M.JAYAPRAKASH (J.P)","party":"IND","votes":"461","pos":"1","pg":"OTH"}},"G04007014":{"name":"ST RAPHAELS","cand":{"canCd":"2","name":"JOHN (M.K.JOHNAPPAN)","party":"INC","votes":"527","pos":"1","pg":"UDF"}},"G04007008":{"name":"THOTTAPPALLY","cand":{"canCd":"1","name":"DINESAN","party":"CPI","votes":"306","pos":"1","pg":"LDF"}},"G04007002":{"name":"VADAYKAKATH","cand":{"canCd":"3","name":"SYAMALAKUMARI.S.T.","party":"INC","votes":"600","pos":"1","pg":"UDF"}},"G04007004":{"name":"VATHARA","cand":{"canCd":"3","name":"RENUKA AJAYAN","party":"INC","votes":"504","pos":"1","pg":"UDF"}}}}






