{"code":"G05015","total":{"LDF":9,"UDF":8,"BJP+":0,"OTH":1},"name":"Thiruvarppu","wardCd":"G05015005","gw":{"G05015011":{"name":"ARUNOOTTIMANGALAM","cand":{"canCd":"4","name":"SUBHAGA TEACHER","party":"INC","votes":"339","pos":"1","pg":"UDF"}},"G05015002":{"name":"CHENGALAM KUNNUMPURAM","cand":{"canCd":"3","name":"SASIDHARAN KUNNAPPALLI","party":"CPI","votes":"372","pos":"1","pg":"LDF"}},"G05015003":{"name":"CHENGALATHUKAVU","cand":{"canCd":"3","name":"RACHEL JACOB","party":"INC","votes":"546","pos":"1","pg":"UDF"}},"G05015018":{"name":"CHENGLAM VAYANASALA","cand":{"canCd":"1","name":"ADV. DEEPTHI","party":"INC","votes":"705","pos":"1","pg":"UDF"}},"G05015009":{"name":"ILLICKAL","cand":{"canCd":"2","name":"ABDUL KAREEM P. A.","party":"CPI","votes":"671","pos":"1","pg":"LDF"}},"G05015012":{"name":"KILIROOR KUNNUMPURAM","cand":{"canCd":"2","name":"P. M. MANI","party":"CPI(M)","votes":"415","pos":"1","pg":"LDF"}},"G05015008":{"name":"KUMMANAM AMBOORAM","cand":{"canCd":"4","name":"KHALID","party":"IUML","votes":"310","pos":"1","pg":"UDF"}},"G05015007":{"name":"KUMMANAM KULAPPURA","cand":{"canCd":"3","name":"THALHATH AYYANKOYIKAL","party":"INC","votes":"440","pos":"1","pg":"UDF"}},"G05015006":{"name":"KUMMANAM MADAKKANDA","cand":{"canCd":"4","name":"O. N. SURESH","party":"INC","votes":"386","pos":"1","pg":"UDF"}},"G05015013":{"name":"MALARICKAL","cand":{"canCd":"3","name":"SHERLY PRASAD","party":"CPI","votes":"451","pos":"1","pg":"LDF"}},"G05015014":{"name":"MEENCHIRA","cand":{"canCd":"1","name":"ASHA SHINIL","party":"CPI(M)","votes":"644","pos":"1","pg":"LDF"}},"G05015001":{"name":"MORCADU","cand":{"canCd":"2","name":"BINCY JACOB","party":"IND","votes":"409","pos":"1","pg":"OTH"}},"G05015015":{"name":"PAKATHUSSERY","cand":{"canCd":"2","name":"JESSY NINAN","party":"CPI(M)","votes":"478","pos":"1","pg":"LDF"}},"G05015010":{"name":"PANCHYATH CENTRAL","cand":{"canCd":"3","name":"VEENA ARUSH","party":"CPI(M)","votes":"370","pos":"1","pg":"LDF"}},"G05015017":{"name":"PARUTHIAKAM","cand":{"canCd":"3","name":"C. T. RAJESH","party":"CPI(M)","votes":"569","pos":"1","pg":"LDF"}},"G05015004":{"name":"PUTHUSSERY","cand":{"canCd":"2","name":"RUBY CHACKO","party":"INC","votes":"559","pos":"1","pg":"UDF"}},"G05015016":{"name":"THIRUVARPPU CENTRAL","cand":{"canCd":"2","name":"K. B. SIVADAS","party":"CPI(M)","votes":"560","pos":"1","pg":"LDF"}},"G05015005":{"name":"THONDAMBRAL","cand":{"canCd":"1","name":"THARA SABU MIDHUNAMKERIL","party":"INC","votes":"496","pos":"1","pg":"UDF"}}}}






