{"code":"G05002","total":{"LDF":10,"UDF":4,"BJP+":0,"OTH":1},"name":"Chempu","wardCd":"G05002013","gw":{"G05002006":{"name":"BRAHMA MANGALAM","cand":{"canCd":"5","name":"REJI MECHERI","party":"INC","votes":"340","pos":"1","pg":"UDF"}},"G05002007":{"name":"CHALUNKAL","cand":{"canCd":"2","name":"VENUGOPAL","party":"CPI(M)","votes":"292","pos":"1","pg":"LDF"}},"G05002011":{"name":"CHEMPU  POST OFFICE","cand":{"canCd":"2","name":"K K RAMESAN","party":"CPI(M)","votes":"562","pos":"1","pg":"LDF"}},"G05002012":{"name":"CHEMPU TOWN","cand":{"canCd":"1","name":"PREMADASAN","party":"CPI","votes":"438","pos":"1","pg":"LDF"}},"G05002004":{"name":"DR. AMBEDKAR","cand":{"canCd":"1","name":"K R CHITHRALEKHA","party":"CPI","votes":"414","pos":"1","pg":"LDF"}},"G05002003":{"name":"ELIAMMEL","cand":{"canCd":"4","name":"SEENA BIJU","party":"CPI(M)","votes":"406","pos":"1","pg":"LDF"}},"G05002009":{"name":"ENADI","cand":{"canCd":"3","name":"LATHA BAIJU","party":"CPI(M)","votes":"359","pos":"1","pg":"LDF"}},"G05002005":{"name":"KALLUKUTHAN KADAVU","cand":{"canCd":"4","name":"ADV. G SHEEBA","party":"CPI(M)","votes":"358","pos":"1","pg":"LDF"}},"G05002001":{"name":"KATTIKUNNU","cand":{"canCd":"4","name":"RASHEED MANGADAN","party":"INC","votes":"571","pos":"1","pg":"UDF"}},"G05002015":{"name":"MAHATMA GANDHI","cand":{"canCd":"4","name":"SMITHA PRINCE","party":"INC","votes":"302","pos":"1","pg":"UDF"}},"G05002014":{"name":"MURINJAPUZHA","cand":{"canCd":"2","name":"LATHA ASHOKAN","party":"CPI(M)","votes":"625","pos":"1","pg":"LDF"}},"G05002002":{"name":"PANACKAL","cand":{"canCd":"3","name":"RAMLATH SALIM","party":"IUML","votes":"370","pos":"1","pg":"UDF"}},"G05002008":{"name":"PARAPPURAM","cand":{"canCd":"1","name":"ASHA BABU","party":"IND","votes":"377","pos":"1","pg":"OTH"}},"G05002010":{"name":"THURUTHUMA","cand":{"canCd":"3","name":"M K SANILKUMAR","party":"CPI","votes":"488","pos":"1","pg":"LDF"}},"G05002013":{"name":"VIJAYODAYAM","cand":{"canCd":"3","name":"LEKHA SURESH","party":"CPI(M)","votes":"489","pos":"1","pg":"LDF"}}}}






