{"code":"G05064","total":{"LDF":11,"UDF":8,"BJP+":1,"OTH":3},"name":"Kanjirappally","wardCd":"G05064017","gw":{"G05064005":{"name":"ANAKKALLU","cand":{"canCd":"4","name":"SHEELA THOMAS THOOMBUNKAL","party":"KCM","votes":"363","pos":"1","pg":"UDF"}},"G05064019":{"name":"ANCHILIPPA","cand":{"canCd":"3","name":"ROSAMMA VETTITHANAM","party":"KC(B)","votes":"412","pos":"1","pg":"LDF"}},"G05064008":{"name":"KANJIRAPPALLY PETTA","cand":{"canCd":"4","name":"M.A.RIBINSHA MADATHIL","party":"CPI(M)","votes":"463","pos":"1","pg":"LDF"}},"G05064011":{"name":"KANJIRAPPALLY SOUTH","cand":{"canCd":"1","name":"NUBIN ANFAL","party":"INC","votes":"567","pos":"1","pg":"UDF"}},"G05064006":{"name":"KANJIRAPPALLY TOWN","cand":{"canCd":"2","name":"BEENA JOBY","party":"NCP","votes":"609","pos":"1","pg":"LDF"}},"G05064002":{"name":"KAPPADU","cand":{"canCd":"1","name":"JACOB JOSE (CHAKOCHAN CHUMAPUNKAL)","party":"IND","votes":"535","pos":"1","pg":"OTH"}},"G05064014":{"name":"KOOVAPPALLY","cand":{"canCd":"1","name":"K.R.THANKAPPAN","party":"CPI(M)","votes":"565","pos":"1","pg":"LDF"}},"G05064015":{"name":"KORATTI","cand":{"canCd":"3","name":"SAJIN.V. VATTAPPALLIL","party":"CPI(M)","votes":"501","pos":"1","pg":"LDF"}},"G05064016":{"name":"MANANGALLOOR","cand":{"canCd":"3","name":"TOMS ANTONY ARYAMANNIL","party":"KCM","votes":"480","pos":"1","pg":"UDF"}},"G05064022":{"name":"MANIDUMKUZHY","cand":{"canCd":"2","name":"KRISHNAKUMARI SASIKUMAR","party":"INC","votes":"527","pos":"1","pg":"UDF"}},"G05064004":{"name":"MANJAPPALLY","cand":{"canCd":"4","name":"VIDYA RAJESH","party":"CPI(M)","votes":"565","pos":"1","pg":"LDF"}},"G05064001":{"name":"MANJUKKULAM","cand":{"canCd":"2","name":"MATHEW JACOB VANIYAPURACKAL(NAINACHEN)","party":"KCM","votes":"606","pos":"1","pg":"UDF"}},"G05064020":{"name":"MANNARAKKAYAM","cand":{"canCd":"2","name":"MERCY MATHEW VETTIYANKAL","party":"IND(LDF)","votes":"405","pos":"1","pg":"LDF"}},"G05064018":{"name":"NJALLAMATTOM","cand":{"canCd":"2","name":"THOMAS JOSEPH(RIJO VALANTHARA)","party":"KCS","votes":"382","pos":"1","pg":"LDF"}},"G05064013":{"name":"PANACHEPPALLY","cand":{"canCd":"2","name":"SURENDRAN KALAYIL","party":"CPI(M)","votes":"619","pos":"1","pg":"LDF"}},"G05064021":{"name":"PANCHAYAT OFFICE WARD","cand":{"canCd":"1","name":"JOSHY THOMAS ANCHANADAN","party":"IND","votes":"808","pos":"1","pg":"OTH"}},"G05064012":{"name":"PATTIMATTOM","cand":{"canCd":"2","name":"MUBEENA NOOR MUHAMMAD M.SC B.ED(SHYNU)","party":"INC","votes":"466","pos":"1","pg":"UDF"}},"G05064010":{"name":"POOTHAKKUZHY","cand":{"canCd":"1","name":"SHAKEELA  NASEER","party":"CPI(M)","votes":"516","pos":"1","pg":"LDF"}},"G05064023":{"name":"THAMPALAKKADU","cand":{"canCd":"2","name":"JANCY GEORGE","party":"INC","votes":"364","pos":"1","pg":"UDF"}},"G05064007":{"name":"THOTTUMUKHAM","cand":{"canCd":"3","name":"SUBIN SALIM(SUNIMON)","party":"IND","votes":"732","pos":"1","pg":"OTH"}},"G05064003":{"name":"VANDANPURAM","cand":{"canCd":"1","name":"MANI RAJU","party":"BJP","votes":"629","pos":"1","pg":"BJP+"}},"G05064009":{"name":"VATTAKAPPARA","cand":{"canCd":"3","name":"NESEEMA  HARIS B.A B .ED","party":"IUML","votes":"315","pos":"1","pg":"UDF"}},"G05064017":{"name":"VIZHIKKATHODU","cand":{"canCd":"3","name":"REJI.O.V (RAJEEV.O.V)","party":"CPI(M)","votes":"455","pos":"1","pg":"LDF"}}}}






