{"code":"G06022","total":{"LDF":4,"UDF":13,"BJP+":0,"OTH":0},"name":"Vannappuram","wardCd":"G06022009","gw":{"G06022007":{"name":"70 ACRE","cand":{"canCd":"1","name":"BINEESHLAL K","party":"INC","votes":"504","pos":"1","pg":"UDF"}},"G06022015":{"name":"KALAYANTHANI","cand":{"canCd":"1","name":"NISSAMOL","party":"IUML","votes":"657","pos":"1","pg":"UDF"}},"G06022010":{"name":"KALIYAR","cand":{"canCd":"1","name":"K H AZIZ","party":"IND(UDF)","votes":"677","pos":"1","pg":"UDF"}},"G06022005":{"name":"KALLIPPARA","cand":{"canCd":"1","name":"SASI K C KONIKKUZHIYIL","party":"KCM","votes":"393","pos":"1","pg":"UDF"}},"G06022008":{"name":"KOOVAPPURAM","cand":{"canCd":"3","name":"LAISAMMA SASI","party":"INC","votes":"438","pos":"1","pg":"UDF"}},"G06022011":{"name":"MULLANKUTHY","cand":{"canCd":"2","name":"SATHYADAS JOSEPH","party":"INC","votes":"617","pos":"1","pg":"UDF"}},"G06022017":{"name":"MULLARINGADU","cand":{"canCd":"2","name":"JOSE T U","party":"INC","votes":"486","pos":"1","pg":"UDF"}},"G06022006":{"name":"MUNDANMUDY","cand":{"canCd":"1","name":"JAINAMMA JOSEPH","party":"INC","votes":"487","pos":"1","pg":"UDF"}},"G06022016":{"name":"ODIYAPARA","cand":{"canCd":"2","name":"JAGATHAMMA VIJAYAN","party":"CPI(M)","votes":"498","pos":"1","pg":"LDF"}},"G06022012":{"name":"ORAKANNI","cand":{"canCd":"3","name":"SHYNI REJI","party":"KCM","votes":"355","pos":"1","pg":"UDF"}},"G06022003":{"name":"PATTAYAKKUDY","cand":{"canCd":"3","name":"SUNNY KALAPURACKAL","party":"KCM","votes":"559","pos":"1","pg":"UDF"}},"G06022002":{"name":"RAJAGIRI","cand":{"canCd":"1","name":"SHEEJA U R","party":"CPI(M)","votes":"446","pos":"1","pg":"LDF"}},"G06022001":{"name":"VALIYAKANDOM","cand":{"canCd":"3","name":"BINCY SAJI","party":"CPI(M)","votes":"491","pos":"1","pg":"LDF"}},"G06022013":{"name":"VANNAPPURAM  TOWN NORTH","cand":{"canCd":"1","name":"LEELA THANKAN","party":"CPI(M)","votes":"555","pos":"1","pg":"LDF"}},"G06022014":{"name":"VANNAPPURAM TOWN SOUTH","cand":{"canCd":"5","name":"RASHEED THOTTUMKAL","party":"IND(UDF)","votes":"441","pos":"1","pg":"UDF"}},"G06022004":{"name":"VELLAKKAYAM","cand":{"canCd":"2","name":"LISSY JOSEPH","party":"INC","votes":"464","pos":"1","pg":"UDF"}},"G06022009":{"name":"VENMATTOM","cand":{"canCd":"4","name":"LAILA RAMESAN","party":"KCM","votes":"610","pos":"1","pg":"UDF"}}}}






