{"code":"G06017","total":{"LDF":5,"UDF":12,"BJP+":0,"OTH":0},"name":"Karunapuram","wardCd":"G06017001","gw":{"G06017004":{"name":"CHAKKAKKANAM","cand":{"canCd":"3","name":"SINDHU MOHANDAS","party":"INC","votes":"432","pos":"1","pg":"UDF"}},"G06017012":{"name":"CHALAKKUDY MEDU","cand":{"canCd":"2","name":"BALAKRISHNAN","party":"CPI(M)","votes":"556","pos":"1","pg":"LDF"}},"G06017009":{"name":"CHENNAKKULAM","cand":{"canCd":"1","name":"TOMY PLAVUVACHATHIL","party":"INC","votes":"531","pos":"1","pg":"UDF"}},"G06017003":{"name":"CHOTTUPARA","cand":{"canCd":"2","name":"BIJU KUMAR","party":"INC","votes":"355","pos":"1","pg":"UDF"}},"G06017010":{"name":"CUMBUMMETTU","cand":{"canCd":"2","name":"RENUKA GOPALAKRISHNAN","party":"KCM","votes":"703","pos":"1","pg":"UDF"}},"G06017008":{"name":"KARUNAPURAM","cand":{"canCd":"2","name":"VINEETHA K.C","party":"INC","votes":"438","pos":"1","pg":"UDF"}},"G06017007":{"name":"KATTEKKANAM","cand":{"canCd":"2","name":"SHIVAPRASAD THANNIPPARA","party":"INC","votes":"576","pos":"1","pg":"UDF"}},"G06017017":{"name":"KOOTTAR","cand":{"canCd":"1","name":"BINUTHA CHANDRAN","party":"CPI(M)","votes":"504","pos":"1","pg":"LDF"}},"G06017013":{"name":"KULATHUMMEDU","cand":{"canCd":"1","name":"JOHN K.G","party":"KCM","votes":"411","pos":"1","pg":"UDF"}},"G06017006":{"name":"KURUVIKKANAM","cand":{"canCd":"1","name":"ANITHA MOHANAN","party":"CPI(M)","votes":"460","pos":"1","pg":"LDF"}},"G06017016":{"name":"KUZHIKKANDOM","cand":{"canCd":"2","name":"JESSY MOL KURIYAN","party":"INC","votes":"469","pos":"1","pg":"UDF"}},"G06017015":{"name":"KUZHITHOLU","cand":{"canCd":"1","name":"AMBILY SIBI","party":"CPI(M)","votes":"378","pos":"1","pg":"LDF"}},"G06017014":{"name":"POTHINKANDOM","cand":{"canCd":"4","name":"RENJU MOL T.N","party":"INC","votes":"345","pos":"1","pg":"UDF"}},"G06017002":{"name":"PRAKASH GRAM","cand":{"canCd":"3","name":"SIDHIQ","party":"INC","votes":"397","pos":"1","pg":"UDF"}},"G06017005":{"name":"RAMAKKALMEDU","cand":{"canCd":"4","name":"SHAMSUDHEEN","party":"CPI(M)","votes":"366","pos":"1","pg":"LDF"}},"G06017011":{"name":"SULTHANMEDU","cand":{"canCd":"3","name":"XAVIOUR JOHN","party":"INC","votes":"578","pos":"1","pg":"UDF"}},"G06017001":{"name":"THOOKKUPALAM","cand":{"canCd":"5","name":"VIJI SHAJI","party":"INC","votes":"399","pos":"1","pg":"UDF"}}}}






