{"code":"G09018","total":{"LDF":10,"UDF":4,"BJP+":1,"OTH":0},"name":"Chalavara","wardCd":"G09018011","gw":{"G09018007":{"name":"CHALAVARA","cand":{"canCd":"1","name":"ABDUL RAHIMAN","party":"IUML","votes":"412","pos":"1","pg":"UDF"}},"G09018005":{"name":"CHALAVARA EAST","cand":{"canCd":"1","name":"C.UNNIKRISHNAN","party":"CPI(M)","votes":"548","pos":"1","pg":"LDF"}},"G09018004":{"name":"CHALAVARA NORTH","cand":{"canCd":"2","name":"NABEESA","party":"IUML","votes":"445","pos":"1","pg":"UDF"}},"G09018013":{"name":"KAYILIYADU","cand":{"canCd":"1","name":"P.AJITHA","party":"CPI(M)","votes":"376","pos":"1","pg":"LDF"}},"G09018010":{"name":"KAYILIYADU MELMURI","cand":{"canCd":"1","name":"N.MANOJ","party":"CPI(M)","votes":"334","pos":"1","pg":"LDF"}},"G09018015":{"name":"MUNDAKKOTTUKURISSI CITY","cand":{"canCd":"3","name":"P.SUNANDA","party":"CPI(M)","votes":"484","pos":"1","pg":"LDF"}},"G09018002":{"name":"MUNDAKKOTTUKURISSI VADAKKUMURI","cand":{"canCd":"1","name":"JAYAN.K.V","party":"BJP","votes":"665","pos":"1","pg":"BJP+"}},"G09018001":{"name":"MUNDAKOTTUKURISSI","cand":{"canCd":"3","name":"RUKKIYA TEACHER.O.","party":"IUML","votes":"426","pos":"1","pg":"UDF"}},"G09018009":{"name":"OLD VILLEGE","cand":{"canCd":"2","name":"C.RAJESH","party":"CPI(M)","votes":"407","pos":"1","pg":"LDF"}},"G09018003":{"name":"PULINTHARA","cand":{"canCd":"3","name":"T.VILASINI","party":"CPI(M)","votes":"502","pos":"1","pg":"LDF"}},"G09018006":{"name":"PULIYANAMKUNNU","cand":{"canCd":"4","name":"M.SANTHOSHKUMAR","party":"INC","votes":"529","pos":"1","pg":"UDF"}},"G09018008":{"name":"THEKKARAPPARA","cand":{"canCd":"2","name":"T.SUDINA","party":"CPI(M)","votes":"433","pos":"1","pg":"LDF"}},"G09018014":{"name":"THRIKKARAMANNA","cand":{"canCd":"2","name":"P.VINEETHA","party":"CPI(M)","votes":"457","pos":"1","pg":"LDF"}},"G09018012":{"name":"VELLACHEERIPARAMBU","cand":{"canCd":"2","name":"P.VALSALA","party":"CPI(M)","votes":"482","pos":"1","pg":"LDF"}},"G09018011":{"name":"VENBALATHUPPADAM","cand":{"canCd":"3","name":"A.P.SATHYAPALAN","party":"CPI(M)","votes":"543","pos":"1","pg":"LDF"}}}}






