{"code":"G13078","total":{"LDF":7,"UDF":6,"BJP+":2,"OTH":0},"name":"Muzhakkunnu","wardCd":"G13078003","gw":{"G13078002":{"name":"AYYAPPAN KAVU","cand":{"canCd":"5","name":"K.V.RASHEED","party":"IUML","votes":"513","pos":"1","pg":"UDF"}},"G13078009":{"name":"GRAMAM","cand":{"canCd":"4","name":"T.V.SINI","party":"CPI","votes":"509","pos":"1","pg":"LDF"}},"G13078007":{"name":"KAKKAYANGADE","cand":{"canCd":"1","name":"PREETHA DINESAN","party":"CPI","votes":"341","pos":"1","pg":"LDF"}},"G13078011":{"name":"KUDUKKAPALAM","cand":{"canCd":"3","name":"RAVEENDRANATHAN.C.K","party":"CPI(M)","votes":"693","pos":"1","pg":"LDF"}},"G13078015":{"name":"KUNNATHOOR","cand":{"canCd":"2","name":"NOORJAHAN.M.M","party":"IUML","votes":"421","pos":"1","pg":"UDF"}},"G13078010":{"name":"MUDAKOZHI","cand":{"canCd":"3","name":"SURENDRAN THACHOLI","party":"CPI(M)","votes":"853","pos":"1","pg":"LDF"}},"G13078012":{"name":"MUZHAKKUNNU","cand":{"canCd":"1","name":"VANAJA.A","party":"CPI(M)","votes":"444","pos":"1","pg":"LDF"}},"G13078013":{"name":"NALLOOR","cand":{"canCd":"3","name":"SHYLAJA RAMAKRISHNAN","party":"INC","votes":"485","pos":"1","pg":"UDF"}},"G13078001":{"name":"OOVVAPALLI","cand":{"canCd":"2","name":"P.P.MUSTAFA","party":"INC","votes":"363","pos":"1","pg":"UDF"}},"G13078005":{"name":"PALA","cand":{"canCd":"3","name":"VINEETHA.M","party":"BJP","votes":"428","pos":"1","pg":"BJP+"}},"G13078014":{"name":"PARAKANDAM","cand":{"canCd":"2","name":"MINI CHANDRAN","party":"CPI(M)","votes":"490","pos":"1","pg":"LDF"}},"G13078006":{"name":"PERUMBUNNA","cand":{"canCd":"4","name":"K.K.SAJEEVAN","party":"INC","votes":"390","pos":"1","pg":"UDF"}},"G13078004":{"name":"PULLANHIYODE","cand":{"canCd":"1","name":"UMESAN.K.K","party":"BJP","votes":"452","pos":"1","pg":"BJP+"}},"G13078008":{"name":"VATTAPOYIL","cand":{"canCd":"1","name":"BABU MASTER","party":"CPI(M)","votes":"412","pos":"1","pg":"LDF"}},"G13078003":{"name":"VILAKODE","cand":{"canCd":"3","name":"MINI.B","party":"IUML","votes":"422","pos":"1","pg":"UDF"}}}}






