{"code":"G13049","total":{"LDF":16,"UDF":5,"BJP+":0,"OTH":0},"name":"Vengad","wardCd":"G13049005","gw":{"G13049007":{"name":"KAITHERIPPOYIL","cand":{"canCd":"1","name":"P AJITHA","party":"CPI(M)","votes":"708","pos":"1","pg":"LDF"}},"G13049002":{"name":"KALLAYI","cand":{"canCd":"1","name":"AABOOTTY MASTER P P ","party":"INC","votes":"762","pos":"1","pg":"UDF"}},"G13049015":{"name":"KEEZHATHUR BALAVADI","cand":{"canCd":"1","name":"P P PRADEESAN","party":"CPI(M)","votes":"642","pos":"1","pg":"LDF"}},"G13049016":{"name":"KEEZHATHUR VAYANASALA","cand":{"canCd":"1","name":"N P KOMALAVALLY","party":"CPI(M)","votes":"733","pos":"1","pg":"LDF"}},"G13049012":{"name":"KELALOOR","cand":{"canCd":"2","name":"C VASANTHA","party":"CPI(M)","votes":"539","pos":"1","pg":"LDF"}},"G13049019":{"name":"KUNNIRIKKA","cand":{"canCd":"2","name":"A RAVINDRAN","party":"CPI(M)","votes":"659","pos":"1","pg":"LDF"}},"G13049017":{"name":"KUZHIYIL PEEDIKA","cand":{"canCd":"1","name":"N SHEENA","party":"CPI(M)","votes":"858","pos":"1","pg":"LDF"}},"G13049018":{"name":"MAILULLY","cand":{"canCd":"2","name":"C REJI","party":"CPI(M)","votes":"627","pos":"1","pg":"LDF"}},"G13049013":{"name":"MAMBARAM","cand":{"canCd":"1","name":"MANOJ ANIYARATH","party":"INC","votes":"803","pos":"1","pg":"UDF"}},"G13049006":{"name":"OORPPALLY","cand":{"canCd":"1","name":"C P ANITHA","party":"CPI(M)","votes":"680","pos":"1","pg":"LDF"}},"G13049010":{"name":"PACHAPOIKA","cand":{"canCd":"1","name":"C SARADA","party":"CPI(M)","votes":"845","pos":"1","pg":"LDF"}},"G13049020":{"name":"PADUVILAYI","cand":{"canCd":"1","name":"K AJITHA","party":"CPI","votes":"535","pos":"1","pg":"LDF"}},"G13049011":{"name":"PARAMBAYI","cand":{"canCd":"2","name":"V KARUNAN","party":"CPI(M)","votes":"610","pos":"1","pg":"LDF"}},"G13049009":{"name":"PATHIRIYAD","cand":{"canCd":"2","name":"K MADHUSOODANAN ","party":"CPI(M)","votes":"892","pos":"1","pg":"LDF"}},"G13049001":{"name":"PATTATHARI","cand":{"canCd":"2","name":"K V PADMINI TEACHER","party":"INC","votes":"658","pos":"1","pg":"UDF"}},"G13049014":{"name":"POYANAD","cand":{"canCd":"1","name":"C LATHA","party":"JD(S)","votes":"630","pos":"1","pg":"LDF"}},"G13049021":{"name":"THATTARI","cand":{"canCd":"2","name":"C P BABYSUDHA TEACHER","party":"IUML","votes":"720","pos":"1","pg":"UDF"}},"G13049008":{"name":"VALANKICHAL","cand":{"canCd":"2","name":"RAJANI C","party":"CPI(M)","votes":"655","pos":"1","pg":"LDF"}},"G13049003":{"name":"VENGAD ANGADI","cand":{"canCd":"4","name":"HUSSAIN VENGAD","party":"IUML","votes":"823","pos":"1","pg":"UDF"}},"G13049004":{"name":"VENGAD METTA","cand":{"canCd":"3","name":"R P SUHASINI","party":"CPI(M)","votes":"688","pos":"1","pg":"LDF"}},"G13049005":{"name":"VENGAD THERU","cand":{"canCd":"3","name":" K SASNKARARAN","party":"CPI(M)","votes":"736","pos":"1","pg":"LDF"}}}}






